unifypy/__init__.py
unifypy/__main__.py
unifypy/cli/__init__.py
unifypy/cli/argument_parser.py
unifypy/cli/interactive/__init__.py
unifypy/cli/interactive/config_definitions.py
unifypy/cli/interactive/input_handlers.py
unifypy/cli/interactive/interactive_menu.py
unifypy/cli/interactive/project_scanner.py
unifypy/cli/interactive/wizard.py
unifypy/core/__init__.py
unifypy/core/config.py
unifypy/core/context.py
unifypy/core/engine.py
unifypy/core/environment.py
unifypy/core/event_bus.py
unifypy/core/events.py
unifypy/core/platforms.py
unifypy/core/plugin.py
unifypy/core/validators/__init__.py
unifypy/core/validators/tool_validator.py
unifypy/platforms/__init__.py
unifypy/platforms/base.py
unifypy/platforms/registry.py
unifypy/platforms/linux/__init__.py
unifypy/platforms/linux/appimage_packager.py
unifypy/platforms/linux/deb_packager.py
unifypy/platforms/linux/rpm_packager.py
unifypy/platforms/macos/__init__.py
unifypy/platforms/macos/dmg_packager.py
unifypy/platforms/macos/post_processor.py
unifypy/platforms/windows/__init__.py
unifypy/platforms/windows/inno_setup.py
unifypy/plugins/__init__.py
unifypy/plugins/auto_rollback_plugin.py
unifypy/plugins/cleanup_plugin.py
unifypy/plugins/config_plugin.py
unifypy/plugins/dry_run_plugin.py
unifypy/plugins/environment_plugin.py
unifypy/plugins/external_plugins_loader.py
unifypy/plugins/packaging_plugin.py
unifypy/plugins/prepare_plugin.py
unifypy/plugins/progress_plugin.py
unifypy/plugins/pyinstaller_plugin.py
unifypy/plugins/rollback_plugin.py
unifypy/plugins/summary_plugin.py
unifypy/plugins/windows_language_plugin.py
unifypy/pyinstaller/__init__.py
unifypy/pyinstaller/config_builder.py
unifypy/templates/ChineseSimplified.isl.template
unifypy/templates/setup.iss.template
unifypy/tools/create-dmg/.this-is-the-create-dmg-repo
unifypy/tools/create-dmg/LICENSE
unifypy/tools/create-dmg/Makefile
unifypy/tools/create-dmg/README.md
unifypy/tools/create-dmg/create-dmg
unifypy/tools/create-dmg/builder/create-dmg.builder
unifypy-2.0.9.dist-info/licenses/LICENSE
unifypy-2.0.9.dist-info/METADATA
unifypy-2.0.9.dist-info/WHEEL
unifypy-2.0.9.dist-info/entry_points.txt
unifypy-2.0.9.dist-info/top_level.txt
unifypy-2.0.9.dist-info/RECORD
