Metadata-Version: 2.4
Name: unifypy
Version: 2.0.9
Summary: UnifyPy 2.0 - Cross-platform Python app packaging tool
Author: Junsen Huang
License: MIT License
Keywords: packaging,pyinstaller,installer,windows,macos,linux
Classifier: Programming Language :: Python :: 3
Classifier: License :: OSI Approved :: MIT License
Classifier: Operating System :: OS Independent
Requires-Python: >=3.8
License-File: LICENSE
Requires-Dist: pyinstaller>=6.0
Requires-Dist: rich>=12.0
Requires-Dist: requests>=2.28
Requires-Dist: packaging>=21.0
Requires-Dist: Pillow
Dynamic: license-file
